harpia/__init__.py
harpia/tropomi/__init__.py
harpia/tropomi/no2/__init__.py
harpia/tropomi/no2/converter.py
harpia/tropomi/no2/cp_completion.py
harpia/tropomi/no2/imputation.py
harpia/tropomi/no2/kriging.py
harpia/tropomi/no2/utils.py
harpia-1.40.dist-info/LICENSE
harpia-1.40.dist-info/METADATA
harpia-1.40.dist-info/WHEEL
harpia-1.40.dist-info/top_level.txt
harpia-1.40.dist-info/RECORD
