Metadata-Version: 2.1
Name: harpia
Version: 1.40
Summary: A Python Package for Development
Home-page: https://github.com/rmsolgi/harpia.git
Author: Ryan Solgi
Author-email: ryan.solgi@gmail.com
Maintainer: Ryan Solgi
Keywords: harpia
Classifier: Programming Language :: Python :: 3
Classifier: License :: OSI Approved :: MIT License
Classifier: Operating System :: OS Independent
Classifier: Topic :: Software Development :: Libraries :: Python Modules
License-File: LICENSE
Requires-Dist: numpy
Requires-Dist: datetime
Requires-Dist: netCDF4
Requires-Dist: pandas
Requires-Dist: geopandas
Requires-Dist: rasterio
